TimePinner/__init__.py
TimePinner/time_pinner.py
TimePinner/time_pinner.pyi
TimePinner-0.2.0.dist-info/LICENSE
TimePinner-0.2.0.dist-info/METADATA
TimePinner-0.2.0.dist-info/WHEEL
TimePinner-0.2.0.dist-info/top_level.txt
TimePinner-0.2.0.dist-info/RECORD
